gdmty_django_users/__init__.py
gdmty_django_users/admin.py
gdmty_django_users/apps.py
gdmty_django_users/decorators.py
gdmty_django_users/managers.py
gdmty_django_users/models.py
gdmty_django_users/permissions.py
gdmty_django_users/serializers.py
gdmty_django_users/settings.py
gdmty_django_users/tests.py
gdmty_django_users/urls.py
gdmty_django_users/viewsets.py
gdmty_django_users/wagtail_forms.py
gdmty_django_users/migrations/0001_initial.py
gdmty_django_users/migrations/0002_alter_user_groups_alter_user_user_permissions_and_more.py
gdmty_django_users/migrations/0003_alter_user_groups_alter_user_user_permissions.py
gdmty_django_users/migrations/__init__.py
gdmty_django_users-24.5.5.dist-info/LICENSE
gdmty_django_users-24.5.5.dist-info/METADATA
gdmty_django_users-24.5.5.dist-info/WHEEL
gdmty_django_users-24.5.5.dist-info/top_level.txt
gdmty_django_users-24.5.5.dist-info/RECORD
