Metadata-Version: 2.1
Name: gdmty-django-users
Version: 24.5.5
Summary: Extension of Django's AbstractBaseUser for user management, using email as user.
Author-email: Gobierno de Monterrey <cesar.benjamin@monterrey.gob.mx>
License: GNU AFFERO GENERAL PUBLIC LICENSE
Project-URL: Homepage, https://github.com/gobiernodigitalmonterrey/gdmty-django-users
Project-URL: Bug Tracker, https://github.com/gobiernodigitalmonterrey/gdmty-django-users/issues
Keywords: django,recaptcha,users
Classifier: License :: OSI Approved :: GNU Affero General Public License v3 or later (AGPLv3+)
Classifier: Programming Language :: Python
Classifier: Programming Language :: Python :: 3
Classifier: Framework :: Django
Classifier: Framework :: Django :: 4
Requires-Python: >=3.9
License-File: LICENSE
Requires-Dist: django >=4.1.13
Requires-Dist: djangorestframework
Requires-Dist: tomli ; python_version < "3.11"
Provides-Extra: dev
Requires-Dist: black ; extra == 'dev'
Requires-Dist: bumpver ; extra == 'dev'
Requires-Dist: isort ; extra == 'dev'
Requires-Dist: pip-tools ; extra == 'dev'
Requires-Dist: pytest ; extra == 'dev'
